<?xml version="1.0" ?><Story>
    <Id>ffcf14a8f73bfe32beebac2d3793dcec</Id>
    <Name></Name>
    <Description> </Description>
    <StartDate> </StartDate>
    <As_a> </As_a>
    <Want_to> </Want_to>
    <So_that> </So_that>
    <EstimateFinishDate> </EstimateFinishDate>
    <EstimateHours> </EstimateHours>
    <ActualHours> </ActualHours>
    <ActualFinish> </ActualFinish>
    <Owner> </Owner>
    <Children List=""/>
    <Parent/>
    <Scribbles><Scribble Color="[1.0,1.0,1.0,1.0]" Id=""/><Scribble Color="[1.0, 1.0, 1.0, 1.0]" Id="271143cd8fd8cf5bb7ab046921fb226f"><![CDATA[[(60.0, 130.00000000000006), (77.0, 170.0), (119.0, 223.0), (149.0, 252.00000000000006), (159.0, 260.0), (160.0, 258.0), (172.99999999999989, 215.00000000000006), (186.0, 173.0), (192.0, 153.00000000000006), (196.0, 151.00000000000006), (230.0, 177.99999999999994), (273.0, 212.0), (352.0, 254.00000000000006), (357.0, 255.0), (359.0, 239.0), (361.0, 202.0), (367.0, 165.0), (368.0, 160.00000000000006), (377.0, 168.0), (423.0, 225.0), (437.0, 236.00000000000006), (438.0, 235.0), (440.0, 202.99999999999994), (442.0, 150.0), (450.0, 113.0), (456.0, 106.0), (463.0, 124.0), (474.0, 158.0), (474.0, 184.0), (453.0, 225.0), (409.0, 250.0), (357.0, 264.99999999999994), (323.0, 266.0), (283.0, 251.0), (252.0, 218.99999999999994), (252.0, 176.00000000000006), (275.0, 163.0), (304.0, 186.0), (309.0, 209.0), (305.0, 232.99999999999994), (280.0, 259.0), (209.0, 251.0), (167.0, 199.00000000000006), (163.0, 129.0), (185.0, 107.00000000000006), (218.0, 119.99999999999997), (241.0, 156.0), (231.0, 209.0), (198.0, 216.99999999999994), (168.99999999999989, 202.99999999999994), (164.0, 190.00000000000006), (166.0, 183.00000000000006), (166.0, 183.00000000000006)]]]></Scribble></Scribbles>
    <TextFields>
        <TextArea Color="[1.0,1.0,1.0,1.0]" Font-Size="" Id="" pos="" size=""/>
    </TextFields>
</Story>